<?xml version="1.0" encoding="UTF-8"?>
<con:testCase xmlns:con="http://eviware.com/soapui/config" id="8e346423-6260-43a1-ac7b-9460e5799bc2" discardOkResults="true" failOnError="true" failTestCaseOnErrors="true" keepSession="false" name="GetPPIPaymentFee TestCase" searchProperties="true" maxResults="0">
  <con:settings id="dda02dd0-6b9e-4055-a456-4a0bd47b7a0d">
    <con:setting id="8e346423-6260-43a1-ac7b-9460e5799bc2fileName">GetPPIPaymentFee-TestCase</con:setting>
  </con:settings>
  <con:testStep type="request" id="b5e9d507-96c7-468f-826a-7fc599f05d4d" name="GetPPIPaymentFee">
    <con:settings/>
    <con:config xmlns:xsi="http://www.w3.org/2001/XMLSchema-instance" xsi:type="con:RequestStep">
      <con:interface>PPIServiceFacadeSoap12</con:interface>
      <con:operation>GetPPIPaymentFee</con:operation>
      <con:request name="GetPPIPaymentFee" id="6d144234-991f-483f-97ff-0c1cfad5aeff" defaultOutgoingWss="" defaultIncomingWss="">
        <con:settings/>
        <con:encoding>UTF-8</con:encoding>
        <con:endpoint>https://demo.velocitypayment.com:443/vgateway/VGatewayWebService</con:endpoint>
        <con:request><![CDATA[<soap:Envelope xmlns:soap="http://www.w3.org/2003/05/soap-envelope" xmlns:ws="https://www.velocitypayment.com/ws" xmlns:ppi="http://www.ePayments.com/PPI">\r
   <soap:Header/>\r
   <soap:Body>\r
      <ws:GetPPIPaymentFee>\r
         <!--Optional:-->\r
         <ws:token>\r
            <!--Optional:-->\r
            <ppi:UserName>?</ppi:UserName>\r
            <!--Optional:-->\r
            <ppi:Password>?</ppi:Password>\r
            <!--Optional:-->\r
            <ppi:PPITransactionRequestId>?</ppi:PPITransactionRequestId>\r
            <!--Optional:-->\r
            <ppi:PPIBusinessEntityIdentifierToken>?</ppi:PPIBusinessEntityIdentifierToken>\r
         </ws:token>\r
         <ws:paymentAmount>?</ws:paymentAmount>\r
         <ws:method>?</ws:method>\r
         <!--Optional:-->\r
         <ws:clientAccountNumber>?</ws:clientAccountNumber>\r
      </ws:GetPPIPaymentFee>\r
   </soap:Body>\r
</soap:Envelope>]]></con:request>
        <con:credentials>
          <con:selectedAuthProfile>No Authorization</con:selectedAuthProfile>
          <con:authType>No Authorization</con:authType>
        </con:credentials>
        <con:jmsConfig JMSDeliveryMode="PERSISTENT"/>
        <con:wsaConfig action="https://www.velocitypayment.com/ws/PPIServiceFacadeSoap/GetPPIPaymentFeeRequest" mustUnderstand="NONE" version="200508"/>
        <con:environmentSpec>
          <con:entry environmentId="340ce76f-4c26-4168-ad5e-9f459d02a685">
            <con:authProfile>Inherit From Parent</con:authProfile>
          </con:entry>
          <con:entry environmentId="e9ddc45e-62b1-4856-b842-795d88eb9ee8">
            <con:authProfile>Inherit From Parent</con:authProfile>
          </con:entry>
          <con:entry environmentId="0bb03ed4-90c7-439a-b3c1-5b9d4c6d7f88">
            <con:authProfile>Inherit From Parent</con:authProfile>
          </con:entry>
          <con:entry environmentId="82a1c8f6-c89d-4861-b0b2-369393cfc3a1">
            <con:authProfile>Inherit From Parent</con:authProfile>
          </con:entry>
          <con:entry environmentId="7a9b6b2f-ab95-4cd7-a195-a7db683f2af4">
            <con:authProfile>Inherit From Parent</con:authProfile>
          </con:entry>
          <con:entry environmentId="1329e3cc-e169-41bd-abb7-aebc80d04a9e">
            <con:authProfile>Inherit From Parent</con:authProfile>
          </con:entry>
        </con:environmentSpec>
      </con:request>
    </con:config>
  </con:testStep>
  <con:properties/>
  <con:reportParameters/>
  <con:environmentSpec>
    <con:entry environmentId="340ce76f-4c26-4168-ad5e-9f459d02a685">
      <con:authProfile>Inherit From Parent</con:authProfile>
    </con:entry>
    <con:entry environmentId="e9ddc45e-62b1-4856-b842-795d88eb9ee8">
      <con:authProfile>Inherit From Parent</con:authProfile>
    </con:entry>
    <con:entry environmentId="0bb03ed4-90c7-439a-b3c1-5b9d4c6d7f88">
      <con:authProfile>Inherit From Parent</con:authProfile>
    </con:entry>
    <con:entry environmentId="82a1c8f6-c89d-4861-b0b2-369393cfc3a1">
      <con:authProfile>Inherit From Parent</con:authProfile>
    </con:entry>
    <con:entry environmentId="7a9b6b2f-ab95-4cd7-a195-a7db683f2af4">
      <con:authProfile>Inherit From Parent</con:authProfile>
    </con:entry>
    <con:entry environmentId="1329e3cc-e169-41bd-abb7-aebc80d04a9e">
      <con:authProfile>Inherit From Parent</con:authProfile>
    </con:entry>
  </con:environmentSpec>
</con:testCase>
